setup.py
lzlla/QR.py
lzlla/__init__.py
lzlla/author.py
lzlla/connecting_points.py
lzlla/connecting_points_tester.py
lzlla/guide.py
lzlla/information_bombardment.py
lzlla/name.py
lzlla.egg-info/PKG-INFO
lzlla.egg-info/SOURCES.txt
lzlla.egg-info/dependency_links.txt
lzlla.egg-info/top_level.txt