Metadata-Version: 2.1
Name: lzlla
Version: 0.4.1
Summary: 一个很会玩的第三方库,更新版本号与更新/修复个数有关
Home-page: https://blog.csdn.net/l15668952150/article/details/124575394
Author: 龙·玛卡巴卡的小推车·卓·弘弘’s_buddy·李/Zhuolong Li
Author-email: liuniandexiaohuo@qq.com
License: UNKNOWN
Platform: UNKNOWN
Classifier: Programming Language :: Python :: 3
Classifier: License :: OSI Approved :: MIT License
Classifier: Operating System :: OS Independent
